{
  "name": "numbers_01_store_prices",
  "turns": [
    {
      "question": "Excuse me, how much is this jacket?",
      "questionAudio": "q000.mp3",
      "answer": "That one's marked at eighty-nine dollars.",
      "answerAudio": "a000.mp3"
    },
    {
      "question": "Is it on sale at all, or is that the regular price?",
      "questionAudio": "q001.mp3",
      "answer": "Yes, actually, it's fifteen dollars off, so it comes to seventy-four.",
      "answerAudio": "a001.mp3"
    },
    {
      "question": "Nice, that's a good discount. What about this scarf next to it?",
      "questionAudio": "q002.mp3",
      "answer": "The scarf is twelve fifty on its own.",
      "answerAudio": "a002.mp3"
    },
    {
      "question": "Would you get a better deal buying the jacket and scarf together?",
      "questionAudio": "q003.mp3",
      "answer": "Yeah, as a set they come to eighty dollars even.",
      "answerAudio": "a003.mp3"
    },
    {
      "question": "That's a solid deal. Does that price already include tax?",
      "questionAudio": "q004.mp3",
      "answer": "No, tax gets added at checkout, so with tax it's about eighty-six.",
      "answerAudio": "a004.mp3"
    },
    {
      "question": "Got it. And how much would shipping add if I have it delivered?",
      "questionAudio": "q005.mp3",
      "answer": "Shipping would add another six ninety-nine on top.",
      "answerAudio": "a005.mp3"
    },
    {
      "question": "I think I'll just carry it home then, that's fine.",
      "questionAudio": "q006.mp3",
      "answer": "Sounds good, I'll ring that up for you now.",
      "answerAudio": "a006.mp3"
    },
    {
      "question": "Actually, how much do I owe you for everything together?",
      "questionAudio": "q007.mp3",
      "answer": "All together, it comes to eighty-six dollars even.",
      "answerAudio": "a007.mp3"
    },
    {
      "question": "Do you take cards, or is it cash only here?",
      "questionAudio": "q008.mp3",
      "answer": "We take cards, whichever is easier for you.",
      "answerAudio": "a008.mp3"
    },
    {
      "question": "Great, I'll just use my card then, thank you.",
      "questionAudio": "q009.mp3",
      "answer": "Perfect, let me get that processed for you right now.",
      "answerAudio": "a009.mp3"
    },
    {
      "question": "Hi, could you check the price on these shoes for me? I don't see a tag.",
      "questionAudio": "q010.mp3",
      "answer": "Sure, let me check -- those are seventy-five dollars a pair.",
      "answerAudio": "a010.mp3"
    },
    {
      "question": "Is there a discount if I buy two pairs instead of one?",
      "questionAudio": "q011.mp3",
      "answer": "Yes, actually, two pairs brings it down to sixty-five each.",
      "answerAudio": "a011.mp3"
    },
    {
      "question": "That's a nice savings. What's the price difference between this pair and the one over there?",
      "questionAudio": "q012.mp3",
      "answer": "This one's about ten dollars more than that other pair.",
      "answerAudio": "a012.mp3"
    },
    {
      "question": "Okay, I think I'll just get the two pairs of these then.",
      "questionAudio": "q013.mp3",
      "answer": "Great choice, that'll come to one hundred thirty for both.",
      "answerAudio": "a013.mp3"
    },
    {
      "question": "Is there a price break if I add a third pair too?",
      "questionAudio": "q014.mp3",
      "answer": "Actually yes, three or more brings each pair down to sixty.",
      "answerAudio": "a014.mp3"
    },
    {
      "question": "Oh, that changes things. Let's do three pairs then.",
      "questionAudio": "q015.mp3",
      "answer": "Perfect, three pairs comes to one hundred eighty total.",
      "answerAudio": "a015.mp3"
    },
    {
      "question": "What's the total with tax included on that?",
      "questionAudio": "q016.mp3",
      "answer": "With tax, it comes out to about one ninety-five.",
      "answerAudio": "a016.mp3"
    },
    {
      "question": "That works for me. Do you know the price per pound on the bags too, in case I need one?",
      "questionAudio": "q017.mp3",
      "answer": "The bags aren't sold by weight, they're just three dollars each.",
      "answerAudio": "a017.mp3"
    },
    {
      "question": "I'll take one bag as well then, thanks.",
      "questionAudio": "q018.mp3",
      "answer": "No problem, I'll add that to your total right now.",
      "answerAudio": "a018.mp3"
    },
    {
      "question": "How much is the whole living room set?",
      "questionAudio": "q019.mp3",
      "answer": "The whole set comes to one hundred twenty dollars.",
      "answerAudio": "a019.mp3"
    },
    {
      "question": "What's the total for everything if I add the lamp too?",
      "questionAudio": "q020.mp3",
      "answer": "With the lamp, your total comes to one thirty-four eighty.",
      "answerAudio": "a020.mp3"
    },
    {
      "question": "Is there a membership discount I could use here?",
      "questionAudio": "q021.mp3",
      "answer": "Yes, with membership it drops to one twenty-seven fifty.",
      "answerAudio": "a021.mp3"
    },
    {
      "question": "How much would express shipping add on top of that?",
      "questionAudio": "q022.mp3",
      "answer": "Express shipping is an extra twelve dollars.",
      "answerAudio": "a022.mp3"
    },
    {
      "question": "Okay, and how much do I need to spend for free shipping instead?",
      "questionAudio": "q023.mp3",
      "answer": "You'd need to spend at least one hundred fifty for that.",
      "answerAudio": "a023.mp3"
    },
    {
      "question": "I'm already past that, so I should qualify then, right?",
      "questionAudio": "q024.mp3",
      "answer": "You're right, that qualifies you for free shipping already.",
      "answerAudio": "a024.mp3"
    },
    {
      "question": "Great, that saves me the twelve dollars then.",
      "questionAudio": "q025.mp3",
      "answer": "Exactly, so your final total is one twenty-seven fifty.",
      "answerAudio": "a025.mp3"
    },
    {
      "question": "What's the price without the membership discount, just curious?",
      "questionAudio": "q026.mp3",
      "answer": "Without it, the same order would be one thirty-four eighty.",
      "answerAudio": "a026.mp3"
    },
    {
      "question": "Good thing I signed up for membership today then.",
      "questionAudio": "q027.mp3",
      "answer": "It really does pay off on bigger orders like this one.",
      "answerAudio": "a027.mp3"
    }
  ]
}