{
  "name": "numbers_07_discounts_percent",
  "turns": [
    {
      "question": "How much of a discount is this sale advertising?",
      "questionAudio": "q000.mp3",
      "answer": "It's twenty percent off everything in the store.",
      "answerAudio": "a000.mp3"
    },
    {
      "question": "Is the whole store included, or just select items?",
      "questionAudio": "q001.mp3",
      "answer": "Just select items, those are marked at thirty percent off instead.",
      "answerAudio": "a001.mp3"
    },
    {
      "question": "What percentage do I save if I use this coupon on top of that?",
      "questionAudio": "q002.mp3",
      "answer": "The coupon takes an extra fifteen percent off your total.",
      "answerAudio": "a002.mp3"
    },
    {
      "question": "Wait, does that stack with the sale price, or is it one or the other?",
      "questionAudio": "q003.mp3",
      "answer": "It stacks, so you'd be saving even more combined.",
      "answerAudio": "a003.mp3"
    },
    {
      "question": "That's great. What about members, do they get an additional discount?",
      "questionAudio": "q004.mp3",
      "answer": "Yes, members get an extra ten percent off on top of that too.",
      "answerAudio": "a004.mp3"
    },
    {
      "question": "I should really sign up for membership then, it sounds worth it.",
      "questionAudio": "q005.mp3",
      "answer": "Honestly, with savings like these, it usually pays for itself fast.",
      "answerAudio": "a005.mp3"
    },
    {
      "question": "What's the interest rate on this loan you're offering?",
      "questionAudio": "q006.mp3",
      "answer": "The interest rate is four point five percent.",
      "answerAudio": "a006.mp3"
    },
    {
      "question": "How does that compare to the rate from last year?",
      "questionAudio": "q007.mp3",
      "answer": "It's actually a bit lower, rates went down about half a percent.",
      "answerAudio": "a007.mp3"
    },
    {
      "question": "What percentage down payment would I need to qualify?",
      "questionAudio": "q008.mp3",
      "answer": "You'll need at least twenty percent down to qualify.",
      "answerAudio": "a008.mp3"
    },
    {
      "question": "And how much would my monthly rate change with a longer term?",
      "questionAudio": "q009.mp3",
      "answer": "A longer term brings the monthly rate down noticeably.",
      "answerAudio": "a009.mp3"
    },
    {
      "question": "What's the current inflation rate factoring into all this?",
      "questionAudio": "q010.mp3",
      "answer": "It's sitting around three point two percent right now.",
      "answerAudio": "a010.mp3"
    },
    {
      "question": "That's helpful context, thank you for explaining all the numbers.",
      "questionAudio": "q011.mp3",
      "answer": "Of course, happy to walk through anything else you're unsure about.",
      "answerAudio": "a011.mp3"
    },
    {
      "question": "What percentage of the class actually passed the final exam?",
      "questionAudio": "q012.mp3",
      "answer": "About ninety percent of the class passed overall.",
      "answerAudio": "a012.mp3"
    },
    {
      "question": "That's pretty high. What was the failure rate exactly then?",
      "questionAudio": "q013.mp3",
      "answer": "The failure rate was only about ten percent this time.",
      "answerAudio": "a013.mp3"
    },
    {
      "question": "How does that compare to last semester's numbers?",
      "questionAudio": "q014.mp3",
      "answer": "Last semester was a bit worse, closer to fifteen percent failed.",
      "answerAudio": "a014.mp3"
    },
    {
      "question": "What do you think caused the improvement this time around?",
      "questionAudio": "q015.mp3",
      "answer": "Honestly, probably the extra review sessions we added before the exam.",
      "answerAudio": "a015.mp3"
    },
    {
      "question": "That makes sense. What percentage of students actually attended those?",
      "questionAudio": "q016.mp3",
      "answer": "About seventy-five percent of the class showed up to at least one.",
      "answerAudio": "a016.mp3"
    },
    {
      "question": "That's a solid turnout. I think we should keep doing those then.",
      "questionAudio": "q017.mp3",
      "answer": "Agreed, I'll plan to add even more next semester.",
      "answerAudio": "a017.mp3"
    }
  ]
}